quick_report.py
rf_quick_dashboard-0.1.5.dist-info/METADATA
rf_quick_dashboard-0.1.5.dist-info/WHEEL
rf_quick_dashboard-0.1.5.dist-info/entry_points.txt
rf_quick_dashboard-0.1.5.dist-info/top_level.txt
rf_quick_dashboard-0.1.5.dist-info/RECORD
