Metadata-Version: 2.1
Name: rf-quick-dashboard
Version: 0.1.5
Summary: A package to generate a simple html dashboard report for Robot Framework using junit xml output
Home-page: UNKNOWN
Author: Chandan Mishra
Author-email: testautomasi@gmail.com
License: UNKNOWN
Platform: UNKNOWN
Classifier: Programming Language :: Python :: 3
Classifier: License :: OSI Approved :: MIT License
Classifier: Operating System :: OS Independent
Requires-Python: >=3.6
Requires-Dist: pandas
Requires-Dist: plotly
Requires-Dist: lxml
